mdtraj/__init__.py
mdtraj/_lprmsd.cp311-win_amd64.pyd
mdtraj/_rmsd.cp311-win_amd64.pyd
mdtraj/io.py
mdtraj/version.py
mdtraj/core/__init__.py
mdtraj/core/element.py
mdtraj/core/residue_names.py
mdtraj/core/selection.py
mdtraj/core/topology.py
mdtraj/core/trajectory.py
mdtraj/core/lib/center.h
mdtraj/core/lib/libtheobald.lib
mdtraj/core/lib/theobald_rmsd.h
mdtraj/formats/__init__.py
mdtraj/formats/amberrst.py
mdtraj/formats/arc.py
mdtraj/formats/binpos.cp311-win_amd64.pyd
mdtraj/formats/dcd.cp311-win_amd64.pyd
mdtraj/formats/dtr.cp311-win_amd64.pyd
mdtraj/formats/gro.py
mdtraj/formats/gsd.py
mdtraj/formats/hdf5.py
mdtraj/formats/hoomdxml.py
mdtraj/formats/lammpstrj.py
mdtraj/formats/lh5.py
mdtraj/formats/mdcrd.py
mdtraj/formats/mol2.py
mdtraj/formats/netcdf.py
mdtraj/formats/openmmxml.py
mdtraj/formats/pdbx.py
mdtraj/formats/prmtop.py
mdtraj/formats/psf.py
mdtraj/formats/registry.py
mdtraj/formats/tng.cp311-win_amd64.pyd
mdtraj/formats/trr.cp311-win_amd64.pyd
mdtraj/formats/xtc.cp311-win_amd64.pyd
mdtraj/formats/xyzfile.py
mdtraj/formats/pdb/__init__.py
mdtraj/formats/pdb/pdbfile.py
mdtraj/formats/pdb/pdbstructure.py
mdtraj/formats/pdb/data/pdbNames.xml
mdtraj/formats/pdb/data/residues.xml
mdtraj/geometry/__init__.py
mdtraj/geometry/_geometry.cp311-win_amd64.pyd
mdtraj/geometry/alignment.py
mdtraj/geometry/angle.py
mdtraj/geometry/contact.py
mdtraj/geometry/dihedral.py
mdtraj/geometry/distance.py
mdtraj/geometry/drid.cp311-win_amd64.pyd
mdtraj/geometry/dssp.py
mdtraj/geometry/hbond.py
mdtraj/geometry/internal.py
mdtraj/geometry/neighborlist.cp311-win_amd64.pyd
mdtraj/geometry/neighbors.cp311-win_amd64.pyd
mdtraj/geometry/order.py
mdtraj/geometry/rdf.py
mdtraj/geometry/rg.py
mdtraj/geometry/sasa.py
mdtraj/geometry/shape.py
mdtraj/geometry/thermodynamic_properties.py
mdtraj/nmr/__init__.py
mdtraj/nmr/scalar_couplings.py
mdtraj/nmr/shift_wrappers.py
mdtraj/reporters/__init__.py
mdtraj/reporters/basereporter.py
mdtraj/reporters/dcdreporter.py
mdtraj_duplicate-1.9.9.dist-info/LICENSE
mdtraj_duplicate-1.9.9.dist-info/METADATA
mdtraj_duplicate-1.9.9.dist-info/WHEEL
mdtraj_duplicate-1.9.9.dist-info/entry_points.txt
mdtraj_duplicate-1.9.9.dist-info/top_level.txt
mdtraj_duplicate-1.9.9.dist-info/RECORD
